{
	"name": "relationship-gvhfhykval",
	"properties": {
		"Name": "relationship-gvhfhykval",
		"EntityType": "RELATIONSHIP",
		"Namespace": {
			"DatabaseName": "Mining_wvf"
		},
		"Origin": {
			"Type": "SPARK"
		},
		"FromTableName": "MaintenanceOperationCost",
		"ToTableName": "MaintenanceOperationCostRelatedParty",
		"ColumnRelationshipInformations": [
			{
				"FromColumnName": "AssetMaintenanceId",
				"ToColumnName": "AssetMaintenanceId"
			}
		],
		"RelationshipType": 0,
		"Properties": {
			"DerivedModelRelationshipInfo": "{\"baseRelationship\":{\"fromEntity\":\"MaintenanceOperationCost.cdm.json/MaintenanceOperationCost\",\"toEntity\":\"MaintenanceOperationCostRelatedParty.cdm.json/MaintenanceOperationCostRelatedParty\",\"joinPairs\":[{\"fromAttribute\":\"AssetMaintenanceId\",\"toAttribute\":\"AssetMaintenanceId\"}]}}"
		}
	},
	"type": "RELATIONSHIP"
}