{
	"name": "relationship-uubyxjigat",
	"properties": {
		"Name": "relationship-uubyxjigat",
		"EntityType": "RELATIONSHIP",
		"Namespace": {
			"DatabaseName": "Mining_wvf"
		},
		"Origin": {
			"Type": "SPARK"
		},
		"FromTableName": "Customer",
		"ToTableName": "ClusterCustomer",
		"ColumnRelationshipInformations": [
			{
				"FromColumnName": "CustomerId",
				"ToColumnName": "CustomerId"
			}
		],
		"RelationshipType": 0,
		"Properties": {
			"DerivedModelRelationshipInfo": "{\"baseRelationship\":{\"fromEntity\":\"Customer.cdm.json/Customer\",\"toEntity\":\"ClusterCustomer.cdm.json/ClusterCustomer\",\"joinPairs\":[{\"fromAttribute\":\"CustomerId\",\"toAttribute\":\"CustomerId\"}]}}"
		}
	},
	"type": "RELATIONSHIP"
}